{
  "name": "get_type_hierarchy",
  "description": "Get the type hierarchy (supertypes and subtypes) for a Java type.\n\nUSAGE: Position on a type, returns full inheritance chain\nOUTPUT: Superclasses, interfaces, and all subtypes\n\nCan be called with either:\n- File position (filePath, line, column) - finds type at cursor\n- Type name (typeName) - looks up type by qualified name\n\nIMPORTANT: Uses ZERO-BASED coordinates when using file position.\n\nRequires load_project to be called first.\n",
  "inputSchema": {
    "type": "object",
    "properties": {
      "column": {
        "type": "integer",
        "description": "Zero-based column number"
      },
      "filePath": {
        "type": "string",
        "description": "Path to source file (for position-based lookup)"
      },
      "line": {
        "type": "integer",
        "description": "Zero-based line number"
      },
      "maxDepth": {
        "type": "integer",
        "description": "Maximum depth of hierarchy to return (default 10)"
      },
      "typeName": {
        "type": "string",
        "description": "Fully qualified type name (alternative to position)"
      }
    }
  }
}